smallgrad/__init__.py
smallgrad/backpropagation.py
smallgrad/build_graph.py
smallgrad/neural_network.py
smallgrad-1.0.2.dist-info/LICENSE
smallgrad-1.0.2.dist-info/METADATA
smallgrad-1.0.2.dist-info/WHEEL
smallgrad-1.0.2.dist-info/entry_points.txt
smallgrad-1.0.2.dist-info/top_level.txt
smallgrad-1.0.2.dist-info/RECORD
