Metadata-Version: 2.1
Name: smallgrad
Version: 1.0.2
Summary: Backpropagation from scratch
Classifier: Development Status :: 5 - Production/Stable
Classifier: Natural Language :: English
Classifier: Operating System :: POSIX :: Linux
Classifier: Operating System :: MacOS :: MacOS X
Classifier: Operating System :: Microsoft :: Windows
Classifier: Programming Language :: Python
Classifier: Programming Language :: Python :: 3.12
Classifier: Programming Language :: Python :: Implementation :: CPython
License-File: LICENSE
Requires-Dist: graphviz==0.20.1
Requires-Dist: pip==24.0
Provides-Extra: dev
Requires-Dist: smallgrad[docs,test]; extra == "dev"
Requires-Dist: mypy; extra == "dev"
Requires-Dist: tox; extra == "dev"
Provides-Extra: docs
Requires-Dist: mkdocs>=1.0.4; extra == "docs"
Provides-Extra: test
Requires-Dist: coverage>=5.0.2; extra == "test"
Requires-Dist: pytest>=6.1.1; extra == "test"
Requires-Dist: pytest-mock; extra == "test"
